tstrings/__init__.py
tstrings_backport-0.1.5.dist-info/WHEEL
tstrings_backport-0.1.5.dist-info/METADATA
tstrings_backport-0.1.5.dist-info/RECORD
