Metadata-Version: 2.3
Name: tstrings-backport
Version: 0.1.5
Summary: Backport of t-strings (PEP 750)
Author: Stefane Fermigier
Author-email: Stefane Fermigier <sf@abilian.com>
Requires-Python: >=3.9
Project-URL: Documentation, https://github.com/abilian/tstrings-backport
Project-URL: Issues, https://github.com/abilian/tstrings-backport/issues
Project-URL: Source, https://github.com/abilian/tstrings-backport
